prana_api_client-0.11.0.dist-info/licenses/LICENSE
prana_local_api_client/__init__.py
prana_local_api_client/exceptions.py
prana_local_api_client/prana_local_api_client.py
prana_local_api_client/models/__init__.py
prana_local_api_client/models/prana_device_info.py
prana_local_api_client/models/prana_fan_type.py
prana_local_api_client/models/prana_state.py
prana_local_api_client/models/prana_switch_type.py
prana_api_client-0.11.0.dist-info/METADATA
prana_api_client-0.11.0.dist-info/WHEEL
prana_api_client-0.11.0.dist-info/top_level.txt
prana_api_client-0.11.0.dist-info/RECORD
