Metadata-Version: 2.4
Name: prana-api-client
Version: 0.11.0
Summary: Async API client for Prana heat recovery ventilator.
Author-email: Prana Developer <devprana18@gmail.com>
License: MIT
Project-URL: Homepage, https://github.com/YourUsername/prana-api-client
Keywords: prana,ventilator,api,async
Requires-Python: >=3.10
License-File: LICENSE
Requires-Dist: aiohttp>=3.9.0
Provides-Extra: dev
Requires-Dist: pytest>=7.0; extra == "dev"
Dynamic: license-file
